valjean/__init__.py
valjean/cambronne/__init__.py
valjean/cambronne/commands/__init__.py
valjean/cambronne/commands/env.py
valjean/cambronne/commands/graph.py
valjean/cambronne/commands/run.py
valjean/cambronne/common.py
valjean/cambronne/main.py
valjean/chrono.py
valjean/config.py
valjean/cosette/__init__.py
valjean/cosette/backends/__init__.py
valjean/cosette/backends/queue.py
valjean/cosette/code.py
valjean/cosette/depgraph.py
valjean/cosette/env.py
valjean/cosette/loop.py
valjean/cosette/pythontask.py
valjean/cosette/rlist.py
valjean/cosette/run.py
valjean/cosette/scheduler.py
valjean/cosette/task.py
valjean/cosette/use.py
valjean/dyn_import.py
valjean/eponine/__init__.py
valjean/eponine/apollo3/__init__.py
valjean/eponine/apollo3/hdf5_picker.py
valjean/eponine/apollo3/hdf5_reader.py
valjean/eponine/browser.py
valjean/eponine/dataset.py
valjean/eponine/tripoli4/__init__.py
valjean/eponine/tripoli4/common.py
valjean/eponine/tripoli4/data_convertor.py
valjean/eponine/tripoli4/depletion.py
valjean/eponine/tripoli4/dump.py
valjean/eponine/tripoli4/grammar.py
valjean/eponine/tripoli4/parse.py
valjean/eponine/tripoli4/parse_debug.py
valjean/eponine/tripoli4/resources/__init__.py
valjean/eponine/tripoli4/resources/depletion/BurnupResults.C
valjean/eponine/tripoli4/resources/depletion/BurnupResults.h
valjean/eponine/tripoli4/resources/depletion/DepletedComposition.C
valjean/eponine/tripoli4/resources/depletion/DepletedComposition.h
valjean/eponine/tripoli4/resources/depletion/MeanBurnupResults.C
valjean/eponine/tripoli4/resources/depletion/MeanBurnupResults.h
valjean/eponine/tripoli4/resources/depletion/__init__.py
valjean/eponine/tripoli4/scan.py
valjean/eponine/tripoli4/transform.py
valjean/eponine/tripoli4/use.py
valjean/fingerprint.py
valjean/gavroche/__init__.py
valjean/gavroche/diagnostics/__init__.py
valjean/gavroche/diagnostics/metadata.py
valjean/gavroche/diagnostics/stats.py
valjean/gavroche/eval_test_task.py
valjean/gavroche/stat_tests/__init__.py
valjean-0.11.0.dist-info/LICENSE
valjean-0.11.0.dist-info/LICENSE_fr
valjean-0.11.0.dist-info/METADATA
valjean-0.11.0.dist-info/WHEEL
valjean-0.11.0.dist-info/entry_points.txt
valjean-0.11.0.dist-info/RECORD
